setup.py
nomad_script.egg-info/PKG-INFO
nomad_script.egg-info/SOURCES.txt
nomad_script.egg-info/dependency_links.txt
nomad_script.egg-info/entry_points.txt
nomad_script.egg-info/requires.txt
nomad_script.egg-info/top_level.txt
script/__init__.py
script/bb_parameters.py
script/bb_parser.py
script/commands.py
script/config.py
script/exceptions.py
script/instances.py
script/nomad.py
script/xml_manager.py