Metadata-Version: 1.1
Name: nomad-script
Version: 1.081
Summary: A python script in order to manage a blackbox with nomad.
Home-page: https://github.com/vlnk/nomad-script
Author: Valentin Laurent
Author-email: vlnk@mail.com
License: MIT
Platform: UNKNOWN
Classifier: Operating System :: POSIX
Classifier: Programming Language :: Python :: 3
Classifier: Programming Language :: Python :: 3.3
Classifier: Programming Language :: Python :: 3.4
